eclip_peak-1.0.20.data/scripts/annotate_peak.pl
eclip_peak-1.0.20.data/scripts/compress_peak.pl
eclip_peak-1.0.20.data/scripts/overlap_peak.pl
eclip_peak-1.0.20.data/scripts/parse_idr_peaks_2.pl
eclip_peak-1.0.20.data/scripts/parse_idr_peaks_3.pl
eclip_peak-1.0.20.data/scripts/peak
eclip_peak-1.0.20.data/scripts/reproducible_peaks_2.pl
eclip_peak-1.0.20.data/scripts/reproducible_peaks_3.pl
peak/__init__.py
peak/annotate_peak.pl
peak/compress_peak.pl
peak/overlap_peak.pl
peak/parse_idr_peaks_2.pl
peak/parse_idr_peaks_3.pl
peak/peak
peak/peak.py
peak/plot.py
peak/reproducible_peaks_2.pl
peak/reproducible_peaks_3.pl
eclip_peak-1.0.20.dist-info/METADATA
eclip_peak-1.0.20.dist-info/WHEEL
eclip_peak-1.0.20.dist-info/top_level.txt
eclip_peak-1.0.20.dist-info/RECORD
