Metadata-Version: 2.1
Name: eclip-peak
Version: 1.0.20
Summary: Pipeline for using IDR to identify a set of reproducible peaks given eClIP dataset with two or three replicates.
Home-page: https://github.com/VanNostrandLab/peak
Author: FEI YUAN
Author-email: fei.yuan@bcm.edu
License: MIT
Keywords: eCLIP-seq,peaks,bioinformatics
Platform: UNKNOWN
Classifier: Programming Language :: Python :: 3
Classifier: License :: OSI Approved :: MIT License
Classifier: Operating System :: POSIX
Requires-Dist: cmder (>=1.0)
Requires-Dist: pandas (>=1.2.3)
Requires-Dist: inflect (>=5.3.0)
Requires-Dist: seqflow (>=0.0.3)
